{
    "total": [
        {
            "id": "1091264685",
            "count": 0
        },
        {
            "id": "100009390112098",
            "count": 0
        },
        {
            "id": "100029522781020",
            "count": 38
        },
        {
            "id": "100048201073164",
            "count": 0
        },
        {
            "id": "100049442207134",
            "count": 0
        },
        {
            "id": "100050648554399",
            "count": 0
        },
        {
            "id": "100051281322127",
            "count": 0
        },
        {
            "id": "100051671851600",
            "count": 0
        },
        {
            "id": "100053462688252",
            "count": 47
        },
        {
            "id": "100055577504700",
            "count": 0
        },
        {
            "id": "100058610380554",
            "count": 0
        },
        {
            "id": "100067461112583",
            "count": 0
        },
        {
            "id": "100067651518439",
            "count": 0
        },
        {
            "id": "100068386661739",
            "count": 0
        },
        {
            "id": "100068528172637",
            "count": 12
        },
        {
            "id": "100069120410504",
            "count": 0
        },
        {
            "id": "100070561115808",
            "count": 0
        },
        {
            "id": "100070963084742",
            "count": 1
        },
        {
            "id": "100071743872139",
            "count": 3
        },
        {
            "id": "100071858751622",
            "count": 0
        },
        {
            "id": "100072780304683",
            "count": 0
        },
        {
            "id": "100073178482519",
            "count": 0
        },
        {
            "id": "100073281651950",
            "count": 14
        },
        {
            "id": "100073407154393",
            "count": 0
        },
        {
            "id": "100073675215311",
            "count": 0
        },
        {
            "id": "100074505462946",
            "count": 0
        },
        {
            "id": "100075001285815",
            "count": 0
        },
        {
            "id": "100075433362702",
            "count": 8
        },
        {
            "id": "100075494896536",
            "count": 0
        },
        {
            "id": "100075495971099",
            "count": 0
        },
        {
            "id": "100076335047606",
            "count": 0
        },
        {
            "id": "100076953107997",
            "count": 23
        },
        {
            "id": "100078266077447",
            "count": 0
        },
        {
            "id": "100079240460229",
            "count": 0
        },
        {
            "id": "100080019060810",
            "count": 0
        },
        {
            "id": "100080180426676",
            "count": 0
        },
        {
            "id": "100081498597793",
            "count": 0
        },
        {
            "id": "100081610565720",
            "count": 0
        },
        {
            "id": "100081635044916",
            "count": 0
        },
        {
            "id": "100081859475531",
            "count": 10
        },
        {
            "id": "100081918601491",
            "count": 6
        },
        {
            "id": "100082314773224",
            "count": 0
        },
        {
            "id": "100082700748212",
            "count": 0
        },
        {
            "id": "100083577052268",
            "count": 0
        },
        {
            "id": "100083580824059",
            "count": 1
        },
        {
            "id": "100083625107902",
            "count": 0
        },
        {
            "id": "100084587593120",
            "count": 0
        },
        {
            "id": "100084763481028",
            "count": 0
        },
        {
            "id": "100084889861466",
            "count": 0
        }
    ],
    "week": [
        {
            "id": "1091264685",
            "count": 0
        },
        {
            "id": "100009390112098",
            "count": 0
        },
        {
            "id": "100029522781020",
            "count": 38
        },
        {
            "id": "100048201073164",
            "count": 0
        },
        {
            "id": "100049442207134",
            "count": 0
        },
        {
            "id": "100050648554399",
            "count": 0
        },
        {
            "id": "100051281322127",
            "count": 0
        },
        {
            "id": "100051671851600",
            "count": 0
        },
        {
            "id": "100053462688252",
            "count": 47
        },
        {
            "id": "100055577504700",
            "count": 0
        },
        {
            "id": "100058610380554",
            "count": 0
        },
        {
            "id": "100067461112583",
            "count": 0
        },
        {
            "id": "100067651518439",
            "count": 0
        },
        {
            "id": "100068386661739",
            "count": 0
        },
        {
            "id": "100068528172637",
            "count": 12
        },
        {
            "id": "100069120410504",
            "count": 0
        },
        {
            "id": "100070561115808",
            "count": 0
        },
        {
            "id": "100070963084742",
            "count": 1
        },
        {
            "id": "100071743872139",
            "count": 3
        },
        {
            "id": "100071858751622",
            "count": 0
        },
        {
            "id": "100072780304683",
            "count": 0
        },
        {
            "id": "100073178482519",
            "count": 0
        },
        {
            "id": "100073281651950",
            "count": 14
        },
        {
            "id": "100073407154393",
            "count": 0
        },
        {
            "id": "100073675215311",
            "count": 0
        },
        {
            "id": "100074505462946",
            "count": 0
        },
        {
            "id": "100075001285815",
            "count": 0
        },
        {
            "id": "100075433362702",
            "count": 8
        },
        {
            "id": "100075494896536",
            "count": 0
        },
        {
            "id": "100075495971099",
            "count": 0
        },
        {
            "id": "100076335047606",
            "count": 0
        },
        {
            "id": "100076953107997",
            "count": 23
        },
        {
            "id": "100078266077447",
            "count": 0
        },
        {
            "id": "100079240460229",
            "count": 0
        },
        {
            "id": "100080019060810",
            "count": 0
        },
        {
            "id": "100080180426676",
            "count": 0
        },
        {
            "id": "100081498597793",
            "count": 0
        },
        {
            "id": "100081610565720",
            "count": 0
        },
        {
            "id": "100081635044916",
            "count": 0
        },
        {
            "id": "100081859475531",
            "count": 10
        },
        {
            "id": "100081918601491",
            "count": 6
        },
        {
            "id": "100082314773224",
            "count": 0
        },
        {
            "id": "100082700748212",
            "count": 0
        },
        {
            "id": "100083577052268",
            "count": 0
        },
        {
            "id": "100083580824059",
            "count": 1
        },
        {
            "id": "100083625107902",
            "count": 0
        },
        {
            "id": "100084587593120",
            "count": 0
        },
        {
            "id": "100084763481028",
            "count": 0
        },
        {
            "id": "100084889861466",
            "count": 0
        }
    ],
    "day": [
        {
            "id": "1091264685",
            "count": 0,
            "name": "Người dùng facebook"
        },
        {
            "id": "100009390112098",
            "count": 0,
            "name": "Người dùng facebook"
        },
        {
            "id": "100029522781020",
            "count": 0,
            "name": "Người dùng facebook"
        },
        {
            "id": "100048201073164",
            "count": 0,
            "name": "Người dùng facebook"
        },
        {
            "id": "100049442207134",
            "count": 0,
            "name": "Người dùng facebook"
        },
        {
            "id": "100050648554399",
            "count": 0,
            "name": "Người dùng facebook"
        },
        {
            "id": "100051281322127",
            "count": 0,
            "name": "Người dùng facebook"
        },
        {
            "id": "100051671851600",
            "count": 0,
            "name": "Người dùng facebook"
        },
        {
            "id": "100053462688252",
            "count": 0,
            "name": "Người dùng facebook"
        },
        {
            "id": "100055577504700",
            "count": 0,
            "name": "Người dùng facebook"
        },
        {
            "id": "100058610380554",
            "count": 0,
            "name": "Người dùng facebook"
        },
        {
            "id": "100067461112583",
            "count": 0,
            "name": "Người dùng facebook"
        },
        {
            "id": "100067651518439",
            "count": 0,
            "name": "Người dùng facebook"
        },
        {
            "id": "100068386661739",
            "count": 0,
            "name": "Người dùng facebook"
        },
        {
            "id": "100068528172637",
            "count": 0,
            "name": "Người dùng facebook"
        },
        {
            "id": "100069120410504",
            "count": 0,
            "name": "Người dùng facebook"
        },
        {
            "id": "100070561115808",
            "count": 0,
            "name": "Người dùng facebook"
        },
        {
            "id": "100070963084742",
            "count": 0,
            "name": "Người dùng facebook"
        },
        {
            "id": "100071743872139",
            "count": 0,
            "name": "Người dùng facebook"
        },
        {
            "id": "100071858751622",
            "count": 0,
            "name": "Người dùng facebook"
        },
        {
            "id": "100072780304683",
            "count": 0,
            "name": "Người dùng facebook"
        },
        {
            "id": "100073178482519",
            "count": 0,
            "name": "Người dùng facebook"
        },
        {
            "id": "100073281651950",
            "count": 0,
            "name": "Người dùng facebook"
        },
        {
            "id": "100073407154393",
            "count": 0,
            "name": "Người dùng facebook"
        },
        {
            "id": "100073675215311",
            "count": 0,
            "name": "Người dùng facebook"
        },
        {
            "id": "100074505462946",
            "count": 0,
            "name": "Người dùng facebook"
        },
        {
            "id": "100075001285815",
            "count": 0,
            "name": "Người dùng facebook"
        },
        {
            "id": "100075433362702",
            "count": 0,
            "name": "Người dùng facebook"
        },
        {
            "id": "100075494896536",
            "count": 0,
            "name": "Người dùng facebook"
        },
        {
            "id": "100075495971099",
            "count": 0,
            "name": "Người dùng facebook"
        },
        {
            "id": "100076335047606",
            "count": 0,
            "name": "Người dùng facebook"
        },
        {
            "id": "100076953107997",
            "count": 0,
            "name": "Người dùng facebook"
        },
        {
            "id": "100078266077447",
            "count": 0,
            "name": "Người dùng facebook"
        },
        {
            "id": "100079240460229",
            "count": 0,
            "name": "Người dùng facebook"
        },
        {
            "id": "100080019060810",
            "count": 0,
            "name": "Người dùng facebook"
        },
        {
            "id": "100080180426676",
            "count": 0,
            "name": "Người dùng facebook"
        },
        {
            "id": "100081498597793",
            "count": 0,
            "name": "Người dùng facebook"
        },
        {
            "id": "100081610565720",
            "count": 0,
            "name": "Người dùng facebook"
        },
        {
            "id": "100081635044916",
            "count": 0,
            "name": "Người dùng facebook"
        },
        {
            "id": "100081859475531",
            "count": 0,
            "name": "Người dùng facebook"
        },
        {
            "id": "100081918601491",
            "count": 0,
            "name": "Người dùng facebook"
        },
        {
            "id": "100082314773224",
            "count": 0,
            "name": "Người dùng facebook"
        },
        {
            "id": "100082700748212",
            "count": 0,
            "name": "Người dùng facebook"
        },
        {
            "id": "100083577052268",
            "count": 0,
            "name": "Người dùng facebook"
        },
        {
            "id": "100083580824059",
            "count": 0,
            "name": "Người dùng facebook"
        },
        {
            "id": "100083625107902",
            "count": 0,
            "name": "Người dùng facebook"
        },
        {
            "id": "100084587593120",
            "count": 0,
            "name": "Người dùng facebook"
        },
        {
            "id": "100084763481028",
            "count": 0,
            "name": "Người dùng facebook"
        },
        {
            "id": "100084889861466",
            "count": 0,
            "name": "Người dùng facebook"
        }
    ],
    "time": 6
}